hpp2pxd/README.MD
hpp2pxd/__init__.py
hpp2pxd/requirements.txt
hpp2pxd/thirdparty.json
hpp2pxd-0.10.dist-info/LICENSE.rst
hpp2pxd-0.10.dist-info/METADATA
hpp2pxd-0.10.dist-info/WHEEL
hpp2pxd-0.10.dist-info/top_level.txt
hpp2pxd-0.10.dist-info/RECORD
