Metadata-Version: 2.1
Name: hpp2pxd
Version: 0.10
Summary: Converts C++ header files into Cython PXD files
Home-page: https://github.com/hansalemaos/hpp2pxd
Author: Johannes Fischer
Author-email: aulasparticularesdealemaosp@gmail.com
License: MIT
Keywords: hpp2pxd,cpp,hpp,pxd,cython
Classifier: Development Status :: 4 - Beta
Classifier: Programming Language :: Python :: 3 :: Only
Classifier: Programming Language :: Python :: 3.10
Classifier: Topic :: Software Development :: Libraries :: Python Modules
Classifier: Topic :: Utilities
License-File: LICENSE.rst
Requires-Dist: numpy
Requires-Dist: pandas
Requires-Dist: regex
Requires-Dist: touchtouch
